selenium_recaptcha_solver/__init__.py
selenium_recaptcha_solver/delay_config.py
selenium_recaptcha_solver/exceptions.py
selenium_recaptcha_solver/services.py
selenium_recaptcha_solver/solver.py
selenium_recaptcha_solver-1.9.1.dist-info/licenses/LICENSE
selenium_recaptcha_solver-1.9.1.dist-info/METADATA
selenium_recaptcha_solver-1.9.1.dist-info/WHEEL
selenium_recaptcha_solver-1.9.1.dist-info/top_level.txt
selenium_recaptcha_solver-1.9.1.dist-info/RECORD
