Metadata-Version: 2.4
Name: selenium-recaptcha-solver
Version: 1.9.1
Home-page: https://github.com/thicccat688/selenium-recaptcha-solver
Download-URL: https://pypi.org/project/selenium-recaptcha-solver
Author: Tomás Perestrelo
Author-email: tomasperestrelo21@gmail.com
License: MIT
Keywords: python,captcha,speech recognition,selenium,web automation
License-File: LICENSE
Requires-Dist: selenium~=4.35.0
Requires-Dist: pydub~=0.25.1
Requires-Dist: SpeechRecognition~=3.8.1
Requires-Dist: requests<2.33.0,>=2.28.1
Dynamic: author
Dynamic: author-email
Dynamic: description
Dynamic: description-content-type
Dynamic: download-url
Dynamic: home-page
Dynamic: keywords
Dynamic: license
Dynamic: license-file
Dynamic: requires-dist
